{
  "parent": "crookedcrooks:recipes/root",
  "rewards": {
    "recipes": [
      "crookedcrooks:thallasium_crook_smithing"
    ]
  },
  "criteria": {
    "has_thallasium": {
      "trigger": "minecraft:inventory_changed",
      "conditions": {
        "items": [
          {
            "items": [
              "betterend:thallasium_ingot"
            ]
          }
        ]
      }
    },
    "has_the_recipe": {
      "trigger": "minecraft:recipe_unlocked",
      "conditions": {
        "recipe": "crookedcrooks:thallasium_crook_smithing"
      }
    }
  },
  "requirements": [
    [
      "has_thallasium",
      "has_the_recipe"
    ]
  ]
}